alvin_cli/__init__.py
alvin_cli/cli.py
alvin_cli/config_management.py
alvin_cli/dbt.py
alvin_cli/entity.py
alvin_cli/impact_analysis.py
alvin_cli/manual_lineage.py
alvin_cli/config/__init__.py
alvin_cli/config/loader.py
alvin_cli/config/settings.py
alvin_cli/platforms/__init__.py
alvin_cli/platforms/add.py
alvin_cli/platforms/platform.py
alvin_cli/schemas/__init__.py
alvin_cli/schemas/models.py
alvin_cli/utils/__init__.py
alvin_cli/utils/api_client.py
alvin_cli/utils/check_sql_impact_analysis.py
alvin_cli/utils/common_arguments.py
alvin_cli/utils/dbt_compile.py
alvin_cli/utils/dbt_deps.py
alvin_cli/utils/git_metadata.py
alvin_cli/utils/helper_functions.py
alvin_cli/utils/utils_dbt.py
alvin_cli/utils/patches/__init__.py
alvin_cli/utils/patches/dbt.py
alvin_cli/utils/patches/sqlfluff.py
alvin_cli-1.3.0.dist-info/LICENSE
alvin_cli-1.3.0.dist-info/METADATA
alvin_cli-1.3.0.dist-info/WHEEL
alvin_cli-1.3.0.dist-info/entry_points.txt
alvin_cli-1.3.0.dist-info/top_level.txt
alvin_cli-1.3.0.dist-info/RECORD
