Metadata-Version: 2.1
Name: alvin-cli
Version: 1.3.0
Summary: Alvin CLI
Home-page: https://github.com/alvindotai/alvin
Classifier: License :: OSI Approved :: MIT License
Classifier: Programming Language :: Python :: 3.7
Classifier: Programming Language :: Python :: 3.8
Classifier: Programming Language :: Python :: 3.9
Classifier: Programming Language :: Python :: Implementation :: PyPy
Requires-Python: >=3.7.1
License-File: LICENSE
Requires-Dist: alvin-api-client
Requires-Dist: mypy ==0.812
Requires-Dist: argh ==0.26.2
Requires-Dist: mutmut ==2.4.0
Requires-Dist: sqlfluff-templater-dbt ==2.1.2
Requires-Dist: sqlfluff ==2.1.2
Requires-Dist: dbt-core ==1.4.0
Requires-Dist: dbt-bigquery ==1.4.0
Requires-Dist: tabulate ==0.8.9
Requires-Dist: PyYAML ==6.0
Requires-Dist: deepmerge ==1.0.1
Requires-Dist: pydantic ==1.9.0
Requires-Dist: pandas ==1.4.2
Requires-Dist: pyhumps ==3.5.3
Requires-Dist: rich ==11.2.0
Requires-Dist: ruamel.yaml ==0.17.21
Requires-Dist: gitpython ==3.1.35
Requires-Dist: requests ==2.31.0
Requires-Dist: typer ==0.4.1
Requires-Dist: python-dotenv ==0.20.0
Requires-Dist: botocore ==1.25.7
Requires-Dist: urllib3 ==1.26.12
